notros2/__init__.py
notros2/_configuration_file_manager.py
notros2/notros2_script.py
notros2/pkg/__init__.py
notros2/pkg/create/__init__.py
notros2/pkg/create/_commons.py
notros2/pkg/create/_package_xml_template.py
notros2/pkg/create/ament_cmake/__init__.py
notros2/pkg/create/ament_cmake/_add_library.py
notros2/pkg/create/ament_cmake/_add_message_only.py
notros2/pkg/create/ament_cmake/_add_node.py
notros2/pkg/create/ament_cmake/_cmakelists_txt.py
notros2/pkg/create/ament_cmake/templates/__init__.py
notros2/pkg/create/ament_cmake/templates/interfaces_only/__init__.py
notros2/pkg/create/ament_cmake/templates/interfaces_only/cmake.py
notros2/pkg/create/ament_cmake/templates/interfaces_only/msg.py
notros2/pkg/create/ament_cmake/templates/interfaces_only/srv.py
notros2/pkg/create/ament_cmake/templates/library/__init__.py
notros2/pkg/create/ament_cmake/templates/library/cmake.py
notros2/pkg/create/ament_cmake/templates/library/cmake_dependencies.py
notros2/pkg/create/ament_cmake/templates/library/cpp.py
notros2/pkg/create/ament_cmake/templates/library/hpp.py
notros2/pkg/create/ament_cmake/templates/simple_node/__init__.py
notros2/pkg/create/ament_cmake/templates/simple_node/cmake.py
notros2/pkg/create/ament_cmake/templates/simple_node/cpp.py
notros2/pkg/create/ament_cmake/templates/simple_node/hpp.py
notros2/pkg/create/ament_cmake/templates/simple_node/main_cpp.py
notros2/pkg/create/ament_python/__init__.py
notros2/pkg/create/ament_python/_add_library.py
notros2/pkg/create/ament_python/_add_node.py
notros2/pkg/create/ament_python/_module_init_py.py
notros2/pkg/create/ament_python/_resource_file.py
notros2/pkg/create/ament_python/_setup_cfg.py
notros2/pkg/create/ament_python/_setup_py.py
notros2/pkg/create/ament_python/templates/__init__.py
notros2/pkg/create/ament_python/templates/library/__init__.py
notros2/pkg/create/ament_python/templates/library/sources_py.py
notros2/pkg/create/ament_python/templates/simple_node/__init__.py
notros2-23.10.4.71955.dist-info/LICENSE
notros2-23.10.4.71955.dist-info/METADATA
notros2-23.10.4.71955.dist-info/WHEEL
notros2-23.10.4.71955.dist-info/entry_points.txt
notros2-23.10.4.71955.dist-info/top_level.txt
notros2-23.10.4.71955.dist-info/zip-safe
notros2-23.10.4.71955.dist-info/RECORD
