Metadata-Version: 2.1
Name: notros2
Version: 23.10.4.71955
Summary: notROS2 utilities.
Maintainer: Murilo M. Marinho
Maintainer-email: murilomarinho@ieee.org
License: MIT
License-File: LICENSE
Requires-Dist: setuptools
